toon_serializer/__init__.py
toon_serializer/decoder.py
toon_serializer/encoder.py
toon_serializer-1.0.0.dist-info/METADATA
toon_serializer-1.0.0.dist-info/WHEEL
toon_serializer-1.0.0.dist-info/licenses/LICENSE
toon_serializer-1.0.0.dist-info/RECORD
