Metadata-Version: 2.4
Name: toon_serializer
Version: 1.0.0
Summary: A Python library for working with TOON format, a compact and human readable serialization format optimized for LLM contexts.
License-File: LICENSE
Requires-Python: >=3.10
